papaltv
