Metadata-Version: 1.0
Name: papaltv
Version: 0.2.2
Summary: Interactive shell Apple Tv controller
Home-page: http://github.com/gdawg/papaltv
Author: Andrew Griffiths
Author-email: andrew.john.griffiths@gmail.com
License: UNKNOWN
Platform: UNKNOWN
